{
    "result": {
        "id": 90401,
        "published": true,
        "path": [
            "Все товары"
        ],
        "children": [
            {
                "id": 90402,
                "published": true,
                "path": [
                    "Все товары",
                    "Авто"
                ],
                "children": [
                    {
                        "id": 90403,
                        "published": true,
                        "path": [
                            "Все товары",
                            "Авто",
                            "Аудио- и видеотехника"
                        ],
                        "children": [
                            {
                                "id": 90404,
                                "published": true,
                                "path": [
                                    "Все товары",
                                    "Авто",
                                    "Аудио- и видеотехника",
                                    "Автомагнитолы"
                                ],
                                "children": []
                            },
                            {
                                "id": 90407,
                                "published": true,
                                "path": [
                                    "Все товары",
                                    "Авто",
                                    "Аудио- и видеотехника",
                                    "Антенны"
                                ],
                                "children": []
                            }
                        ]
                    }
                ]
            },
            {
                "id": 8475840,
                "published": true,
                "path": [
                    "Все товары",
                    "Аптека"
                ],
                "children": [
                    {
                        "id": 90521,
                        "published": true,
                        "path": [
                            "Все товары",
                            "Аптека",
                            "Витамины и минералы"
                        ],
                        "children": []
                    }
                ]
            }
        ]
    }
}
